README.rst
setup.py
sshkeys/__init__.py
sshkeys.egg-info/PKG-INFO
sshkeys.egg-info/SOURCES.txt
sshkeys.egg-info/dependency_links.txt
sshkeys.egg-info/requires.txt
sshkeys.egg-info/top_level.txt