Metadata-Version: 1.0
Name: sshkeys
Version: 0.3
Summary: A library for working with public SSH keys.
Home-page: http://github.com/mbr/sshkeys
Author: Marc Brinkmann
Author-email: git@marcbrinkmann.de
License: MIT
Platform: UNKNOWN
